{"name":"Titania, Prideful Queen","attribute":"Water","type":"Resonator","cmc":7,"racesOrTraits":["Twelve Apostles","Fairy"],"text":"Flying\nAs you play this card, you may rest any number of resonators you control. You may pay 2 less to play this card for each resonator rested this way.\nOther water resonators and other Fairy resonators you control gain [+200/+200].","set":"Battle for Attoractia","code":"BFA-045","rarity":"R","thumbnailImage":"../assets/img/cards/BFA/045.jpg","cardImage":"http://db.fowtcg.us/cards/bfa/045.jpg"}