{"name":"Space-Time Collapse","attribute":"Dark","type":"Spell:Chant","cmc":2,"racesOrTraits":[],"text":"Choose one - Destroy target resonator or regalia; or destroy up to one target resonator and up to one target regalia. Choose the second only if your J/ruler is \"Conqueror of the Black Moon, Gill Lapis\" or \"Gill Lapis, the Primogenitor\"","set":"The Moonlit Savior","code":"TMS-083-R","rarity":"R","thumbnailImage":"http://db.fowtcg.us/thumbs/tms/083.jpg","cardImage":"http://db.fowtcg.us/cards/tms/083.jpg"}